tls_client_for_chatGPT/__init__.py
tls_client_for_chatGPT/__version__.py
tls_client_for_chatGPT/cffi.py
tls_client_for_chatGPT/cookies.py
tls_client_for_chatGPT/exceptions.py
tls_client_for_chatGPT/response.py
tls_client_for_chatGPT/sessions.py
tls_client_for_chatGPT/structures.py
tls_client_for_chatGPT/dependencies/__init__.py
tls_client_for_chatGPT/dependencies/tls-client-32.dll
tls_client_for_chatGPT/dependencies/tls-client-64.dll
tls_client_for_chatGPT/dependencies/tls-client-amd64.so
tls_client_for_chatGPT/dependencies/tls-client-arm64.dylib
tls_client_for_chatGPT/dependencies/tls-client-x86.dylib
tls_client_for_chatGPT/dependencies/tls-client-x86.so
tls_client_for_chatGPT-0.2.dist-info/LICENSE
tls_client_for_chatGPT-0.2.dist-info/METADATA
tls_client_for_chatGPT-0.2.dist-info/WHEEL
tls_client_for_chatGPT-0.2.dist-info/top_level.txt
tls_client_for_chatGPT-0.2.dist-info/RECORD
